algoauditor/__init__.py
algoauditor/gender_tag_dataset.py
algoauditor/nlg.py
algoauditor/nlp.py
algoauditor/public/nlg.html
algoauditor/public/nlg.js
algoauditor/public/nlg_json.js
algoauditor/public/styles.css
algoauditor/utils/__init__.py
algoauditor/utils/api_response_handler.py
algoauditor-0.0.2.dist-info/WHEEL
algoauditor-0.0.2.dist-info/METADATA
algoauditor-0.0.2.dist-info/RECORD
