Metadata-Version: 2.1
Name: algoauditor
Version: 0.0.2
Summary: Lethical AI Python Library with cloud support
Home-page: https://lethical.ai
License: Proprietary
Keywords: AI/ML,discrimination,bias,detection,debiasing
Author: Amanl04
Author-email: amanlodha423@outlook.com
Maintainer: Aman Lodha
Maintainer-email: aman@lethical.ai
Requires-Python: >=3.6,<4.0
Classifier: License :: Other/Proprietary License
Classifier: Programming Language :: Python :: 3
Classifier: Programming Language :: Python :: 3.6
Classifier: Programming Language :: Python :: 3.7
Classifier: Programming Language :: Python :: 3.8
Requires-Dist: numpy (>=1.19.4,<2.0.0)
Requires-Dist: requests (>=2.25.0,<3.0.0)
